pybitespodcast/__init__.py
pybitespodcast/search.py
pybitespodcast-0.1.0.dist-info/entry_points.txt
pybitespodcast-0.1.0.dist-info/WHEEL
pybitespodcast-0.1.0.dist-info/METADATA
pybitespodcast-0.1.0.dist-info/RECORD
