Metadata-Version: 2.1
Name: pybitespodcast
Version: 0.1.0
Summary: 
Home-page: https://github.com/bbelderbos/pybitespodcast
License: MIT
Keywords: pybites,podcast,search
Author: Bob Belderbos
Author-email: bobbelderbos@gmail.com
Requires-Python: >=3.9,<4.0
Classifier: License :: OSI Approved :: MIT License
Classifier: Programming Language :: Python :: 3
Classifier: Programming Language :: Python :: 3.9
Requires-Dist: feedparser (>=6.0.2,<7.0.0)
Project-URL: Repository, https://github.com/bbelderbos/pybitespodcast
